torchgeometry/__init__.py
torchgeometry/conversions.py
torchgeometry/depth_warper.py
torchgeometry/homography_warper.py
torchgeometry/imgwarp.py
torchgeometry/pinhole.py
torchgeometry/utils.py
torchgeometry-0.1.1.dist-info/LICENSE.txt
torchgeometry-0.1.1.dist-info/METADATA
torchgeometry-0.1.1.dist-info/RECORD
torchgeometry-0.1.1.dist-info/WHEEL
torchgeometry-0.1.1.dist-info/top_level.txt
torchgeometry-0.1.1.dist-info/zip-safe
