Metadata-Version: 2.1
Name: torchgeometry
Version: 0.1.1
Summary: differential geometric computer vision for deep learning
Home-page: https://github.com/arraiy/torchgeometry
Author: Edgar Riba
Author-email: edgar.riba@gmail.com
License: BSD
Platform: UNKNOWN
Requires-Dist: torch (==1.0.0)
